AutoBrewML/__init__.py
AutoBrewML/test.py
AutoBrewML/version.py
AutoBrewML-0.45.dist-info/LICENSE.txt
AutoBrewML-0.45.dist-info/METADATA
AutoBrewML-0.45.dist-info/WHEEL
AutoBrewML-0.45.dist-info/top_level.txt
AutoBrewML-0.45.dist-info/RECORD
