Metadata-Version: 2.1
Name: AutoBrewML
Version: 0.45
Summary: With AutoBrewML Framework the time it takes to get production-ready ML models with great ease and efficiency highly accelerates.
Author: Sreeja Deb
Author-email: srde@microsoft.com
Project-URL: AutoBrewML GitHub, https://github.com/microsoft/AutoBrewML
Classifier: Programming Language :: Python :: 3
Classifier: License :: OSI Approved :: MIT License
Classifier: Operating System :: OS Independent
License-File: LICENSE.txt
Requires-Dist: numpy
Requires-Dist: llvmlite
Requires-Dist: numba
Requires-Dist: scipy
Requires-Dist: pandas
Requires-Dist: sklearn
Requires-Dist: pandas-profiling
Requires-Dist: MarkupSafe
Requires-Dist: imblearn
Requires-Dist: scikit-learn
Requires-Dist: fairlearn
Requires-Dist: tpot
Requires-Dist: pyod
